data_helpers/__init__.py
data_helpers/cls_construction.py
data_helpers/cls_parsing.py
data_helpers/comparisons.py
data_helpers/data_loaders.py
data_helpers/dictionary_helpers.py
data_helpers/diff.py
data_helpers/fill_np_array.py
data_helpers/functional_helpers.py
data_helpers/list_helpers.py
data_helpers/meta_type.py
data_helpers/snapshot_helpers.py
data_helpers/time_data.py
data_helpers/util.py
data_helpers/version.py
data_helpers/encoders/__init__.py
data_helpers/encoders/encoders.py
data_helpers/encoders/meta_class_encoder.py
tests/__init__.py
tests/cls_construction_test.py
tests/cls_parsing_test.py
tests/comparisons_test.py
tests/dictionary_helpers_test.py
tests/diff_test.py
tests/fill_np_array_test.py
tests/functional_helpers_test.py
tests/list_helpers_test.py
tests/time_data_test.py
tests/util_test.py
tests/encoders/__init__.py
tests/encoders/encoders_test.py
tests/encoders/meta_class_encoder_test.py
tests/snapshots/__init__.py
tests/snapshots/snap_cls_construction_test.py
data_helpers-0.1.32.dist-info/METADATA
data_helpers-0.1.32.dist-info/WHEEL
data_helpers-0.1.32.dist-info/top_level.txt
data_helpers-0.1.32.dist-info/RECORD
