Metadata-Version: 2.1
Name: data_helpers
Version: 0.1.32
Summary: A set of helpers for working with various datatypes
Author: sbland
Author-email: sblandcouk@gmail.com
Classifier: Programming Language :: Python :: 3.7
Classifier: Operating System :: OS Independent
Requires-Dist: numpy
Provides-Extra: test
Requires-Dist: pytest; extra == "test"
Requires-Dist: numpy; extra == "test"
